[{"id":"13457504583","type":"PushEvent","actor":{"id":21791,"login":"wilhelm-murdoch","display_login":"wilhelm-murdoch","gravatar_id":"","url":"https://api.github.com/users/wilhelm-murdoch","avatar_url":"https://avatars.githubusercontent.com/u/21791?"},"repo":{"id":426035190,"name":"wilhelm-murdoch/wilhelm.codes","url":"https://api.github.com/repos/wilhelm-murdoch/wilhelm.codes"},"payload":{"repository_id":426035190,"push_id":35745691747,"ref":"refs/heads/main","head":"58c7811f36f25dcf060a0ae093a18bd939012905","before":"f7f1a5128c2f8475789618c68f5717680aef5d90"},"public":true,"created_at":"2026-06-17T09:45:38Z"},{"id":"13457305869","type":"PushEvent","actor":{"id":21791,"login":"wilhelm-murdoch","display_login":"wilhelm-murdoch","gravatar_id":"","url":"https://api.github.com/users/wilhelm-murdoch","avatar_url":"https://avatars.githubusercontent.com/u/21791?"},"repo":{"id":426035190,"name":"wilhelm-murdoch/wilhelm.codes","url":"https://api.github.com/repos/wilhelm-murdoch/wilhelm.codes"},"payload":{"repository_id":426035190,"push_id":35745493105,"ref":"refs/heads/main","head":"f7f1a5128c2f8475789618c68f5717680aef5d90","before":"9b8a7ab070ce7362828c7bd1c5c9175bd8fc3d84"},"public":true,"created_at":"2026-06-17T09:41:21Z"},{"id":"13457150031","type":"DeleteEvent","actor":{"id":21791,"login":"wilhelm-murdoch","display_login":"wilhelm-murdoch","gravatar_id":"","url":"https://api.github.com/users/wilhelm-murdoch","avatar_url":"https://avatars.githubusercontent.com/u/21791?"},"repo":{"id":426035190,"name":"wilhelm-murdoch/wilhelm.codes","url":"https://api.github.com/repos/wilhelm-murdoch/wilhelm.codes"},"payload":{"ref":"dark-mode-theme-selection","ref_type":"branch","full_ref":"refs/heads/dark-mode-theme-selection","pusher_type":"user"},"public":true,"created_at":"2026-06-17T09:38:02Z"},{"id":"10798671582","type":"PullRequestEvent","actor":{"id":21791,"login":"wilhelm-murdoch","display_login":"wilhelm-murdoch","gravatar_id":"","url":"https://api.github.com/users/wilhelm-murdoch","avatar_url":"https://avatars.githubusercontent.com/u/21791?"},"repo":{"id":426035190,"name":"wilhelm-murdoch/wilhelm.codes","url":"https://api.github.com/repos/wilhelm-murdoch/wilhelm.codes"},"payload":{"action":"merged","number":11,"pull_request":{"url":"https://api.github.com/repos/wilhelm-murdoch/wilhelm.codes/pulls/11","id":3882326867,"number":11,"head":{"ref":"dark-mode-theme-selection","sha":"0f7ddce8657a5c99a147d510b2a0966a8af8a617","repo":{"id":426035190,"url":"https://api.github.com/repos/wilhelm-murdoch/wilhelm.codes","name":"wilhelm.codes"}},"base":{"ref":"main","sha":"0bab61b4b2dfe5bd23eb3b0dd4b9edd2f3943354","repo":{"id":426035190,"url":"https://api.github.com/repos/wilhelm-murdoch/wilhelm.codes","name":"wilhelm.codes"}}}},"public":true,"created_at":"2026-06-17T09:37:52Z"},{"id":"13457143655","type":"PushEvent","actor":{"id":21791,"login":"wilhelm-murdoch","display_login":"wilhelm-murdoch","gravatar_id":"","url":"https://api.github.com/users/wilhelm-murdoch","avatar_url":"https://avatars.githubusercontent.com/u/21791?"},"repo":{"id":426035190,"name":"wilhelm-murdoch/wilhelm.codes","url":"https://api.github.com/repos/wilhelm-murdoch/wilhelm.codes"},"payload":{"repository_id":426035190,"push_id":35745330885,"ref":"refs/heads/main","head":"9b8a7ab070ce7362828c7bd1c5c9175bd8fc3d84","before":"0bab61b4b2dfe5bd23eb3b0dd4b9edd2f3943354"},"public":true,"created_at":"2026-06-17T09:37:53Z"},{"id":"13457127688","type":"PushEvent","actor":{"id":21791,"login":"wilhelm-murdoch","display_login":"wilhelm-murdoch","gravatar_id":"","url":"https://api.github.com/users/wilhelm-murdoch","avatar_url":"https://avatars.githubusercontent.com/u/21791?"},"repo":{"id":426035190,"name":"wilhelm-murdoch/wilhelm.codes","url":"https://api.github.com/repos/wilhelm-murdoch/wilhelm.codes"},"payload":{"repository_id":426035190,"push_id":35745314924,"ref":"refs/heads/dark-mode-theme-selection","head":"0f7ddce8657a5c99a147d510b2a0966a8af8a617","before":"29b715852c05fd510f66c45092e9279a7ca7a774"},"public":true,"created_at":"2026-06-17T09:37:33Z"},{"id":"10798577090","type":"PullRequestEvent","actor":{"id":21791,"login":"wilhelm-murdoch","display_login":"wilhelm-murdoch","gravatar_id":"","url":"https://api.github.com/users/wilhelm-murdoch","avatar_url":"https://avatars.githubusercontent.com/u/21791?"},"repo":{"id":426035190,"name":"wilhelm-murdoch/wilhelm.codes","url":"https://api.github.com/repos/wilhelm-murdoch/wilhelm.codes"},"payload":{"action":"opened","number":11,"pull_request":{"url":"https://api.github.com/repos/wilhelm-murdoch/wilhelm.codes/pulls/11","id":3882326867,"number":11,"head":{"ref":"dark-mode-theme-selection","sha":"0f7ddce8657a5c99a147d510b2a0966a8af8a617","repo":{"id":426035190,"url":"https://api.github.com/repos/wilhelm-murdoch/wilhelm.codes","name":"wilhelm.codes"}},"base":{"ref":"main","sha":"0bab61b4b2dfe5bd23eb3b0dd4b9edd2f3943354","repo":{"id":426035190,"url":"https://api.github.com/repos/wilhelm-murdoch/wilhelm.codes","name":"wilhelm.codes"}}}},"public":true,"created_at":"2026-06-17T09:35:43Z"},{"id":"13456557952","type":"DeleteEvent","actor":{"id":21791,"login":"wilhelm-murdoch","display_login":"wilhelm-murdoch","gravatar_id":"","url":"https://api.github.com/users/wilhelm-murdoch","avatar_url":"https://avatars.githubusercontent.com/u/21791?"},"repo":{"id":426035190,"name":"wilhelm-murdoch/wilhelm.codes","url":"https://api.github.com/repos/wilhelm-murdoch/wilhelm.codes"},"payload":{"ref":"particle-MEmitter","ref_type":"branch","full_ref":"refs/heads/particle-MEmitter","pusher_type":"user"},"public":true,"created_at":"2026-06-17T09:25:23Z"},{"id":"13456555439","type":"PushEvent","actor":{"id":21791,"login":"wilhelm-murdoch","display_login":"wilhelm-murdoch","gravatar_id":"","url":"https://api.github.com/users/wilhelm-murdoch","avatar_url":"https://avatars.githubusercontent.com/u/21791?"},"repo":{"id":426035190,"name":"wilhelm-murdoch/wilhelm.codes","url":"https://api.github.com/repos/wilhelm-murdoch/wilhelm.codes"},"payload":{"repository_id":426035190,"push_id":35744742239,"ref":"refs/heads/main","head":"0bab61b4b2dfe5bd23eb3b0dd4b9edd2f3943354","before":"3a2dcce23bf8545261adf8e1a8af690f511de314"},"public":true,"created_at":"2026-06-17T09:25:19Z"},{"id":"10798113813","type":"PullRequestEvent","actor":{"id":21791,"login":"wilhelm-murdoch","display_login":"wilhelm-murdoch","gravatar_id":"","url":"https://api.github.com/users/wilhelm-murdoch","avatar_url":"https://avatars.githubusercontent.com/u/21791?"},"repo":{"id":426035190,"name":"wilhelm-murdoch/wilhelm.codes","url":"https://api.github.com/repos/wilhelm-murdoch/wilhelm.codes"},"payload":{"action":"merged","number":10,"pull_request":{"url":"https://api.github.com/repos/wilhelm-murdoch/wilhelm.codes/pulls/10","id":3882248182,"number":10,"head":{"ref":"particle-MEmitter","sha":"f050d8906747134fcbcf6e2570e499b0a03f5c57","repo":{"id":426035190,"url":"https://api.github.com/repos/wilhelm-murdoch/wilhelm.codes","name":"wilhelm.codes"}},"base":{"ref":"main","sha":"3a2dcce23bf8545261adf8e1a8af690f511de314","repo":{"id":426035190,"url":"https://api.github.com/repos/wilhelm-murdoch/wilhelm.codes","name":"wilhelm.codes"}}}},"public":true,"created_at":"2026-06-17T09:25:18Z"},{"id":"10798098793","type":"PullRequestEvent","actor":{"id":21791,"login":"wilhelm-murdoch","display_login":"wilhelm-murdoch","gravatar_id":"","url":"https://api.github.com/users/wilhelm-murdoch","avatar_url":"https://avatars.githubusercontent.com/u/21791?"},"repo":{"id":426035190,"name":"wilhelm-murdoch/wilhelm.codes","url":"https://api.github.com/repos/wilhelm-murdoch/wilhelm.codes"},"payload":{"action":"opened","number":10,"pull_request":{"url":"https://api.github.com/repos/wilhelm-murdoch/wilhelm.codes/pulls/10","id":3882248182,"number":10,"head":{"ref":"particle-MEmitter","sha":"f050d8906747134fcbcf6e2570e499b0a03f5c57","repo":{"id":426035190,"url":"https://api.github.com/repos/wilhelm-murdoch/wilhelm.codes","name":"wilhelm.codes"}},"base":{"ref":"main","sha":"3a2dcce23bf8545261adf8e1a8af690f511de314","repo":{"id":426035190,"url":"https://api.github.com/repos/wilhelm-murdoch/wilhelm.codes","name":"wilhelm.codes"}}}},"public":true,"created_at":"2026-06-17T09:24:57Z"},{"id":"13456499910","type":"CreateEvent","actor":{"id":21791,"login":"wilhelm-murdoch","display_login":"wilhelm-murdoch","gravatar_id":"","url":"https://api.github.com/users/wilhelm-murdoch","avatar_url":"https://avatars.githubusercontent.com/u/21791?"},"repo":{"id":426035190,"name":"wilhelm-murdoch/wilhelm.codes","url":"https://api.github.com/repos/wilhelm-murdoch/wilhelm.codes"},"payload":{"ref":"particle-MEmitter","ref_type":"branch","full_ref":"refs/heads/particle-MEmitter","master_branch":"main","description":"All source files for my personal website.","pusher_type":"user"},"public":true,"created_at":"2026-06-17T09:24:10Z"},{"id":"13456426406","type":"PushEvent","actor":{"id":21791,"login":"wilhelm-murdoch","display_login":"wilhelm-murdoch","gravatar_id":"","url":"https://api.github.com/users/wilhelm-murdoch","avatar_url":"https://avatars.githubusercontent.com/u/21791?"},"repo":{"id":426035190,"name":"wilhelm-murdoch/wilhelm.codes","url":"https://api.github.com/repos/wilhelm-murdoch/wilhelm.codes"},"payload":{"repository_id":426035190,"push_id":35744613234,"ref":"refs/heads/dark-mode-theme-selection","head":"29b715852c05fd510f66c45092e9279a7ca7a774","before":"af04c8737c01a3123189bacdc83c79159e3aede7"},"public":true,"created_at":"2026-06-17T09:22:36Z"},{"id":"13407766351","type":"CreateEvent","actor":{"id":21791,"login":"wilhelm-murdoch","display_login":"wilhelm-murdoch","gravatar_id":"","url":"https://api.github.com/users/wilhelm-murdoch","avatar_url":"https://avatars.githubusercontent.com/u/21791?"},"repo":{"id":426035190,"name":"wilhelm-murdoch/wilhelm.codes","url":"https://api.github.com/repos/wilhelm-murdoch/wilhelm.codes"},"payload":{"ref":"dark-mode-theme-selection","ref_type":"branch","full_ref":"refs/heads/dark-mode-theme-selection","master_branch":"main","description":"All source files for my personal website.","pusher_type":"user"},"public":true,"created_at":"2026-06-16T12:58:22Z"},{"id":"13405052776","type":"PushEvent","actor":{"id":21791,"login":"wilhelm-murdoch","display_login":"wilhelm-murdoch","gravatar_id":"","url":"https://api.github.com/users/wilhelm-murdoch","avatar_url":"https://avatars.githubusercontent.com/u/21791?"},"repo":{"id":426035190,"name":"wilhelm-murdoch/wilhelm.codes","url":"https://api.github.com/repos/wilhelm-murdoch/wilhelm.codes"},"payload":{"repository_id":426035190,"push_id":35692909929,"ref":"refs/heads/main","head":"3a2dcce23bf8545261adf8e1a8af690f511de314","before":"e79870928a00311c49ddf8d0ebca2e9294414c5d"},"public":true,"created_at":"2026-06-16T12:02:50Z"},{"id":"13404304592","type":"PushEvent","actor":{"id":21791,"login":"wilhelm-murdoch","display_login":"wilhelm-murdoch","gravatar_id":"","url":"https://api.github.com/users/wilhelm-murdoch","avatar_url":"https://avatars.githubusercontent.com/u/21791?"},"repo":{"id":426035190,"name":"wilhelm-murdoch/wilhelm.codes","url":"https://api.github.com/repos/wilhelm-murdoch/wilhelm.codes"},"payload":{"repository_id":426035190,"push_id":35692161910,"ref":"refs/heads/main","head":"e79870928a00311c49ddf8d0ebca2e9294414c5d","before":"22d49f9e5e51580ff3083c0391f9619e7adefc35"},"public":true,"created_at":"2026-06-16T11:47:13Z"},{"id":"13403573876","type":"PushEvent","actor":{"id":21791,"login":"wilhelm-murdoch","display_login":"wilhelm-murdoch","gravatar_id":"","url":"https://api.github.com/users/wilhelm-murdoch","avatar_url":"https://avatars.githubusercontent.com/u/21791?"},"repo":{"id":426035190,"name":"wilhelm-murdoch/wilhelm.codes","url":"https://api.github.com/repos/wilhelm-murdoch/wilhelm.codes"},"payload":{"repository_id":426035190,"push_id":35691431044,"ref":"refs/heads/main","head":"22d49f9e5e51580ff3083c0391f9619e7adefc35","before":"de1b4e0f932bf23dd864ac16d6ab7350fd28f8f0"},"public":true,"created_at":"2026-06-16T11:30:58Z"},{"id":"13402738256","type":"PushEvent","actor":{"id":21791,"login":"wilhelm-murdoch","display_login":"wilhelm-murdoch","gravatar_id":"","url":"https://api.github.com/users/wilhelm-murdoch","avatar_url":"https://avatars.githubusercontent.com/u/21791?"},"repo":{"id":426035190,"name":"wilhelm-murdoch/wilhelm.codes","url":"https://api.github.com/repos/wilhelm-murdoch/wilhelm.codes"},"payload":{"repository_id":426035190,"push_id":35690594233,"ref":"refs/heads/main","head":"de1b4e0f932bf23dd864ac16d6ab7350fd28f8f0","before":"839b6eddf30a59268abe8c26b3b4b94ce4aa1a65"},"public":true,"created_at":"2026-06-16T11:12:24Z"},{"id":"13399906454","type":"PushEvent","actor":{"id":21791,"login":"wilhelm-murdoch","display_login":"wilhelm-murdoch","gravatar_id":"","url":"https://api.github.com/users/wilhelm-murdoch","avatar_url":"https://avatars.githubusercontent.com/u/21791?"},"repo":{"id":426035190,"name":"wilhelm-murdoch/wilhelm.codes","url":"https://api.github.com/repos/wilhelm-murdoch/wilhelm.codes"},"payload":{"repository_id":426035190,"push_id":35687760657,"ref":"refs/heads/main","head":"839b6eddf30a59268abe8c26b3b4b94ce4aa1a65","before":"0f983d15ea56d18c2c15ca55db0bcc8815a0c4d0"},"public":true,"created_at":"2026-06-16T10:09:06Z"},{"id":"10735630826","type":"DiscussionEvent","actor":{"id":81026895,"login":"giscus[bot]","display_login":"giscus","gravatar_id":"","url":"https://api.github.com/users/giscus[bot]","avatar_url":"https://avatars.githubusercontent.com/u/81026895?"},"repo":{"id":426035190,"name":"wilhelm-murdoch/wilhelm.codes","url":"https://api.github.com/repos/wilhelm-murdoch/wilhelm.codes"},"payload":{"action":"created","discussion":{"repository_url":"https://api.github.com/repos/wilhelm-murdoch/wilhelm.codes","category":{"id":43263339,"node_id":"DIC_kwDOGWTH9s4ClCVr","repository_id":426035190,"emoji":":speech_balloon:","name":"Blog Comments","description":"All discussions for blog articles will be managed within this category.","created_at":"2024-12-08T13:39:13.000Z","updated_at":"2024-12-08T13:42:36.000Z","slug":"blog-comments","is_answerable":false},"answer_html_url":null,"answer_chosen_at":null,"answer_chosen_by":null,"html_url":"https://github.com/wilhelm-murdoch/wilhelm.codes/discussions/9","id":10265084,"node_id":"D_kwDOGWTH9s4AnKH8","number":9,"title":"A Changelog That Builds Itself · Wilhelm Codes","user":{"login":"giscus[bot]","id":81026895,"node_id":"MDM6Qm90ODEwMjY4OTU=","avatar_url":"https://avatars.githubusercontent.com/in/106117?v=4","gravatar_id":"","url":"https://api.github.com/users/giscus%5Bbot%5D","html_url":"https://github.com/apps/giscus","followers_url":"https://api.github.com/users/giscus%5Bbot%5D/followers","following_url":"https://api.github.com/users/giscus%5Bbot%5D/following{/other_user}","gists_url":"https://api.github.com/users/giscus%5Bbot%5D/gists{/gist_id}","starred_url":"https://api.github.com/users/giscus%5Bbot%5D/starred{/owner}{/repo}","subscriptions_url":"https://api.github.com/users/giscus%5Bbot%5D/subscriptions","organizations_url":"https://api.github.com/users/giscus%5Bbot%5D/orgs","repos_url":"https://api.github.com/users/giscus%5Bbot%5D/repos","events_url":"https://api.github.com/users/giscus%5Bbot%5D/events{/privacy}","received_events_url":"https://api.github.com/users/giscus%5Bbot%5D/received_events","type":"Bot","user_view_type":"public","site_admin":false},"labels":[],"state":"open","state_reason":null,"locked":false,"comments":0,"created_at":"2026-06-16T04:54:56Z","updated_at":"2026-06-16T04:55:31Z","active_lock_reason":null,"body":"# A Changelog That Builds Itself · Wilhelm Codes\n\nThis site has a changelog page. It’s not one I write by hand as it builds itself from my activity on GitHub every time the site deploys. I think …\n\nhttps://wilhelm.codes/blog/a-changelog-that-builds-itself/\n\n<!-- sha1: 899ded5e31db37c7f34cf95ce42c8ca42a82d177 -->","reactions":{"url":"https://api.github.com/repos/wilhelm-murdoch/wilhelm.codes/discussions/9/reactions","total_count":0,"+1":0,"-1":0,"laugh":0,"hooray":0,"confused":0,"heart":0,"rocket":0,"eyes":0},"timeline_url":"https://api.github.com/repos/wilhelm-murdoch/wilhelm.codes/discussions/9/timeline"}},"public":true,"created_at":"2026-06-16T04:54:56Z"},{"id":"13378055608","type":"PushEvent","actor":{"id":21791,"login":"wilhelm-murdoch","display_login":"wilhelm-murdoch","gravatar_id":"","url":"https://api.github.com/users/wilhelm-murdoch","avatar_url":"https://avatars.githubusercontent.com/u/21791?"},"repo":{"id":426035190,"name":"wilhelm-murdoch/wilhelm.codes","url":"https://api.github.com/repos/wilhelm-murdoch/wilhelm.codes"},"payload":{"repository_id":426035190,"push_id":35665910275,"ref":"refs/heads/main","head":"0f983d15ea56d18c2c15ca55db0bcc8815a0c4d0","before":"46304a452b2b0b9f99d386b864f9540502eba959"},"public":true,"created_at":"2026-06-15T23:54:49Z"},{"id":"13376910397","type":"PushEvent","actor":{"id":21791,"login":"wilhelm-murdoch","display_login":"wilhelm-murdoch","gravatar_id":"","url":"https://api.github.com/users/wilhelm-murdoch","avatar_url":"https://avatars.githubusercontent.com/u/21791?"},"repo":{"id":426035190,"name":"wilhelm-murdoch/wilhelm.codes","url":"https://api.github.com/repos/wilhelm-murdoch/wilhelm.codes"},"payload":{"repository_id":426035190,"push_id":35664767981,"ref":"refs/heads/main","head":"46304a452b2b0b9f99d386b864f9540502eba959","before":"914c20e6f141a1e8a01a5f849d8f2e4ea2f51f38"},"public":true,"created_at":"2026-06-15T23:15:06Z"},{"id":"13376902332","type":"CreateEvent","actor":{"id":21791,"login":"wilhelm-murdoch","display_login":"wilhelm-murdoch","gravatar_id":"","url":"https://api.github.com/users/wilhelm-murdoch","avatar_url":"https://avatars.githubusercontent.com/u/21791?"},"repo":{"id":426035190,"name":"wilhelm-murdoch/wilhelm.codes","url":"https://api.github.com/repos/wilhelm-murdoch/wilhelm.codes"},"payload":{"ref":"interstitial-timeline-events","ref_type":"branch","full_ref":"refs/heads/interstitial-timeline-events","master_branch":"main","description":"All source files for my personal website.","pusher_type":"user"},"public":true,"created_at":"2026-06-15T23:14:51Z"},{"id":"13351211825","type":"PushEvent","actor":{"id":21791,"login":"wilhelm-murdoch","display_login":"wilhelm-murdoch","gravatar_id":"","url":"https://api.github.com/users/wilhelm-murdoch","avatar_url":"https://avatars.githubusercontent.com/u/21791?"},"repo":{"id":426035190,"name":"wilhelm-murdoch/wilhelm.codes","url":"https://api.github.com/repos/wilhelm-murdoch/wilhelm.codes"},"payload":{"repository_id":426035190,"push_id":35639098757,"ref":"refs/heads/main","head":"914c20e6f141a1e8a01a5f849d8f2e4ea2f51f38","before":"83792b4d74722d0ff3f3382f4682df67a5eff440"},"public":true,"created_at":"2026-06-15T13:32:40Z"},{"id":"13350675515","type":"PushEvent","actor":{"id":21791,"login":"wilhelm-murdoch","display_login":"wilhelm-murdoch","gravatar_id":"","url":"https://api.github.com/users/wilhelm-murdoch","avatar_url":"https://avatars.githubusercontent.com/u/21791?"},"repo":{"id":426035190,"name":"wilhelm-murdoch/wilhelm.codes","url":"https://api.github.com/repos/wilhelm-murdoch/wilhelm.codes"},"payload":{"repository_id":426035190,"push_id":35638562423,"ref":"refs/heads/main","head":"83792b4d74722d0ff3f3382f4682df67a5eff440","before":"70cea05b55f27ced8e93de3e1bf233c29f55a3f2"},"public":true,"created_at":"2026-06-15T13:22:24Z"},{"id":"13350012897","type":"PushEvent","actor":{"id":21791,"login":"wilhelm-murdoch","display_login":"wilhelm-murdoch","gravatar_id":"","url":"https://api.github.com/users/wilhelm-murdoch","avatar_url":"https://avatars.githubusercontent.com/u/21791?"},"repo":{"id":426035190,"name":"wilhelm-murdoch/wilhelm.codes","url":"https://api.github.com/repos/wilhelm-murdoch/wilhelm.codes"},"payload":{"repository_id":426035190,"push_id":35637900169,"ref":"refs/heads/main","head":"70cea05b55f27ced8e93de3e1bf233c29f55a3f2","before":"460fc914ceec7d5bc425bf9d491a790cdf2462ed"},"public":true,"created_at":"2026-06-15T13:09:41Z"},{"id":"13349947648","type":"PushEvent","actor":{"id":21791,"login":"wilhelm-murdoch","display_login":"wilhelm-murdoch","gravatar_id":"","url":"https://api.github.com/users/wilhelm-murdoch","avatar_url":"https://avatars.githubusercontent.com/u/21791?"},"repo":{"id":426035190,"name":"wilhelm-murdoch/wilhelm.codes","url":"https://api.github.com/repos/wilhelm-murdoch/wilhelm.codes"},"payload":{"repository_id":426035190,"push_id":35637835239,"ref":"refs/heads/main","head":"460fc914ceec7d5bc425bf9d491a790cdf2462ed","before":"8489f54489644a7969fedf4660684bef7d946b10"},"public":true,"created_at":"2026-06-15T13:08:24Z"},{"id":"13349605870","type":"PushEvent","actor":{"id":21791,"login":"wilhelm-murdoch","display_login":"wilhelm-murdoch","gravatar_id":"","url":"https://api.github.com/users/wilhelm-murdoch","avatar_url":"https://avatars.githubusercontent.com/u/21791?"},"repo":{"id":426035190,"name":"wilhelm-murdoch/wilhelm.codes","url":"https://api.github.com/repos/wilhelm-murdoch/wilhelm.codes"},"payload":{"repository_id":426035190,"push_id":35637493866,"ref":"refs/heads/main","head":"8489f54489644a7969fedf4660684bef7d946b10","before":"63f82916507dff12cc2d9ba15928d589942dfd50"},"public":true,"created_at":"2026-06-15T13:01:48Z"},{"id":"13340838155","type":"PushEvent","actor":{"id":21791,"login":"wilhelm-murdoch","display_login":"wilhelm-murdoch","gravatar_id":"","url":"https://api.github.com/users/wilhelm-murdoch","avatar_url":"https://avatars.githubusercontent.com/u/21791?"},"repo":{"id":426035190,"name":"wilhelm-murdoch/wilhelm.codes","url":"https://api.github.com/repos/wilhelm-murdoch/wilhelm.codes"},"payload":{"repository_id":426035190,"push_id":35628726059,"ref":"refs/heads/main","head":"63f82916507dff12cc2d9ba15928d589942dfd50","before":"fced434f7073317bf730198e12b1f8df78914df5"},"public":true,"created_at":"2026-06-15T09:51:54Z"},{"id":"13331397437","type":"CreateEvent","actor":{"id":21791,"login":"wilhelm-murdoch","display_login":"wilhelm-murdoch","gravatar_id":"","url":"https://api.github.com/users/wilhelm-murdoch","avatar_url":"https://avatars.githubusercontent.com/u/21791?"},"repo":{"id":426035190,"name":"wilhelm-murdoch/wilhelm.codes","url":"https://api.github.com/repos/wilhelm-murdoch/wilhelm.codes"},"payload":{"ref":"activity-graph","ref_type":"branch","full_ref":"refs/heads/activity-graph","master_branch":"main","description":"All source files for my personal website.","pusher_type":"user"},"public":true,"created_at":"2026-06-15T06:09:19Z"},{"id":"13328660796","type":"PushEvent","actor":{"id":21791,"login":"wilhelm-murdoch","display_login":"wilhelm-murdoch","gravatar_id":"","url":"https://api.github.com/users/wilhelm-murdoch","avatar_url":"https://avatars.githubusercontent.com/u/21791?"},"repo":{"id":426035190,"name":"wilhelm-murdoch/wilhelm.codes","url":"https://api.github.com/repos/wilhelm-murdoch/wilhelm.codes"},"payload":{"repository_id":426035190,"push_id":35616538809,"ref":"refs/heads/main","head":"fced434f7073317bf730198e12b1f8df78914df5","before":"302c7f7ec2045ed55f9b062f7a9c3164d3de95f5"},"public":true,"created_at":"2026-06-15T04:40:37Z"},{"id":"13328092495","type":"PushEvent","actor":{"id":21791,"login":"wilhelm-murdoch","display_login":"wilhelm-murdoch","gravatar_id":"","url":"https://api.github.com/users/wilhelm-murdoch","avatar_url":"https://avatars.githubusercontent.com/u/21791?"},"repo":{"id":426035190,"name":"wilhelm-murdoch/wilhelm.codes","url":"https://api.github.com/repos/wilhelm-murdoch/wilhelm.codes"},"payload":{"repository_id":426035190,"push_id":35615969924,"ref":"refs/heads/main","head":"302c7f7ec2045ed55f9b062f7a9c3164d3de95f5","before":"1792b68f5bb88c2301d79958ce08351684ee3186"},"public":true,"created_at":"2026-06-15T04:20:47Z"},{"id":"13327899315","type":"PushEvent","actor":{"id":21791,"login":"wilhelm-murdoch","display_login":"wilhelm-murdoch","gravatar_id":"","url":"https://api.github.com/users/wilhelm-murdoch","avatar_url":"https://avatars.githubusercontent.com/u/21791?"},"repo":{"id":426035190,"name":"wilhelm-murdoch/wilhelm.codes","url":"https://api.github.com/repos/wilhelm-murdoch/wilhelm.codes"},"payload":{"repository_id":426035190,"push_id":35615776628,"ref":"refs/heads/main","head":"1792b68f5bb88c2301d79958ce08351684ee3186","before":"134a1d7b0de6c64b4c07c078f21d224800dbbf53"},"public":true,"created_at":"2026-06-15T04:14:07Z"},{"id":"13304328855","type":"PushEvent","actor":{"id":21791,"login":"wilhelm-murdoch","display_login":"wilhelm-murdoch","gravatar_id":"","url":"https://api.github.com/users/wilhelm-murdoch","avatar_url":"https://avatars.githubusercontent.com/u/21791?"},"repo":{"id":426035190,"name":"wilhelm-murdoch/wilhelm.codes","url":"https://api.github.com/repos/wilhelm-murdoch/wilhelm.codes"},"payload":{"repository_id":426035190,"push_id":35592174649,"ref":"refs/heads/main","head":"134a1d7b0de6c64b4c07c078f21d224800dbbf53","before":"f84d7cd4452cc300724942b5c0b4ee3ab8bc69ab"},"public":true,"created_at":"2026-06-14T13:09:06Z"},{"id":"13302829878","type":"PushEvent","actor":{"id":21791,"login":"wilhelm-murdoch","display_login":"wilhelm-murdoch","gravatar_id":"","url":"https://api.github.com/users/wilhelm-murdoch","avatar_url":"https://avatars.githubusercontent.com/u/21791?"},"repo":{"id":426035190,"name":"wilhelm-murdoch/wilhelm.codes","url":"https://api.github.com/repos/wilhelm-murdoch/wilhelm.codes"},"payload":{"repository_id":426035190,"push_id":35590672971,"ref":"refs/heads/main","head":"f84d7cd4452cc300724942b5c0b4ee3ab8bc69ab","before":"eb484fb5aaf2ffb135bfde98658ce5228cb0fce6"},"public":true,"created_at":"2026-06-14T12:10:26Z"},{"id":"10667874777","type":"IssueCommentEvent","actor":{"id":21791,"login":"wilhelm-murdoch","display_login":"wilhelm-murdoch","gravatar_id":"","url":"https://api.github.com/users/wilhelm-murdoch","avatar_url":"https://avatars.githubusercontent.com/u/21791?"},"repo":{"id":426035190,"name":"wilhelm-murdoch/wilhelm.codes","url":"https://api.github.com/repos/wilhelm-murdoch/wilhelm.codes"},"payload":{"action":"created","issue":{"url":"https://api.github.com/repos/wilhelm-murdoch/wilhelm.codes/issues/8","repository_url":"https://api.github.com/repos/wilhelm-murdoch/wilhelm.codes","labels_url":"https://api.github.com/repos/wilhelm-murdoch/wilhelm.codes/issues/8/labels{/name}","comments_url":"https://api.github.com/repos/wilhelm-murdoch/wilhelm.codes/issues/8/comments","events_url":"https://api.github.com/repos/wilhelm-murdoch/wilhelm.codes/issues/8/events","html_url":"https://github.com/wilhelm-murdoch/wilhelm.codes/pull/8","id":4658022615,"node_id":"PR_kwDOGWTH9s7mL6Be","number":8,"title":"chore: modernize all the tooling and implement some nice design updates","user":{"login":"wilhelm-murdoch","id":21791,"node_id":"MDQ6VXNlcjIxNzkx","avatar_url":"https://avatars.githubusercontent.com/u/21791?v=4","gravatar_id":"","url":"https://api.github.com/users/wilhelm-murdoch","html_url":"https://github.com/wilhelm-murdoch","followers_url":"https://api.github.com/users/wilhelm-murdoch/followers","following_url":"https://api.github.com/users/wilhelm-murdoch/following{/other_user}","gists_url":"https://api.github.com/users/wilhelm-murdoch/gists{/gist_id}","starred_url":"https://api.github.com/users/wilhelm-murdoch/starred{/owner}{/repo}","subscriptions_url":"https://api.github.com/users/wilhelm-murdoch/subscriptions","organizations_url":"https://api.github.com/users/wilhelm-murdoch/orgs","repos_url":"https://api.github.com/users/wilhelm-murdoch/repos","events_url":"https://api.github.com/users/wilhelm-murdoch/events{/privacy}","received_events_url":"https://api.github.com/users/wilhelm-murdoch/received_events","type":"User","user_view_type":"public","site_admin":false},"labels":[],"state":"closed","locked":false,"assignees":[],"milestone":null,"comments":1,"created_at":"2026-06-14T05:22:58Z","updated_at":"2026-06-14T11:50:44Z","closed_at":"2026-06-14T11:50:43Z","assignee":null,"active_lock_reason":null,"draft":false,"pull_request":{"url":"https://api.github.com/repos/wilhelm-murdoch/wilhelm.codes/pulls/8","html_url":"https://github.com/wilhelm-murdoch/wilhelm.codes/pull/8","diff_url":"https://github.com/wilhelm-murdoch/wilhelm.codes/pull/8.diff","patch_url":"https://github.com/wilhelm-murdoch/wilhelm.codes/pull/8.patch","merged_at":null},"body":null,"reactions":{"url":"https://api.github.com/repos/wilhelm-murdoch/wilhelm.codes/issues/8/reactions","total_count":0,"+1":0,"-1":0,"laugh":0,"hooray":0,"confused":0,"heart":0,"rocket":0,"eyes":0},"timeline_url":"https://api.github.com/repos/wilhelm-murdoch/wilhelm.codes/issues/8/timeline","performed_via_github_app":null,"state_reason":null},"comment":{"url":"https://api.github.com/repos/wilhelm-murdoch/wilhelm.codes/issues/comments/4701654624","html_url":"https://github.com/wilhelm-murdoch/wilhelm.codes/pull/8#issuecomment-4701654624","issue_url":"https://api.github.com/repos/wilhelm-murdoch/wilhelm.codes/issues/8","id":4701654624,"node_id":"IC_kwDOGWTH9s8AAAABGD2OYA","user":{"login":"wilhelm-murdoch","id":21791,"node_id":"MDQ6VXNlcjIxNzkx","avatar_url":"https://avatars.githubusercontent.com/u/21791?v=4","gravatar_id":"","url":"https://api.github.com/users/wilhelm-murdoch","html_url":"https://github.com/wilhelm-murdoch","followers_url":"https://api.github.com/users/wilhelm-murdoch/followers","following_url":"https://api.github.com/users/wilhelm-murdoch/following{/other_user}","gists_url":"https://api.github.com/users/wilhelm-murdoch/gists{/gist_id}","starred_url":"https://api.github.com/users/wilhelm-murdoch/starred{/owner}{/repo}","subscriptions_url":"https://api.github.com/users/wilhelm-murdoch/subscriptions","organizations_url":"https://api.github.com/users/wilhelm-murdoch/orgs","repos_url":"https://api.github.com/users/wilhelm-murdoch/repos","events_url":"https://api.github.com/users/wilhelm-murdoch/events{/privacy}","received_events_url":"https://api.github.com/users/wilhelm-murdoch/received_events","type":"User","user_view_type":"public","site_admin":false},"created_at":"2026-06-14T11:50:43Z","updated_at":"2026-06-14T11:50:43Z","body":"Yeah, nah, we're not going this route 😅 ","reactions":{"url":"https://api.github.com/repos/wilhelm-murdoch/wilhelm.codes/issues/comments/4701654624/reactions","total_count":0,"+1":0,"-1":0,"laugh":0,"hooray":0,"confused":0,"heart":0,"rocket":0,"eyes":0},"performed_via_github_app":null}},"public":true,"created_at":"2026-06-14T11:50:43Z"},{"id":"10667874776","type":"PullRequestEvent","actor":{"id":21791,"login":"wilhelm-murdoch","display_login":"wilhelm-murdoch","gravatar_id":"","url":"https://api.github.com/users/wilhelm-murdoch","avatar_url":"https://avatars.githubusercontent.com/u/21791?"},"repo":{"id":426035190,"name":"wilhelm-murdoch/wilhelm.codes","url":"https://api.github.com/repos/wilhelm-murdoch/wilhelm.codes"},"payload":{"action":"closed","number":8,"pull_request":{"url":"https://api.github.com/repos/wilhelm-murdoch/wilhelm.codes/pulls/8","id":3861880926,"number":8,"head":{"ref":"modernize","sha":"c549f29f71dc13066cb21410d68797c19332e7be","repo":{"id":426035190,"url":"https://api.github.com/repos/wilhelm-murdoch/wilhelm.codes","name":"wilhelm.codes"}},"base":{"ref":"main","sha":"300d4fceae16492238dba21ccec5d66a0ec8c8dc","repo":{"id":426035190,"url":"https://api.github.com/repos/wilhelm-murdoch/wilhelm.codes","name":"wilhelm.codes"}}}},"public":true,"created_at":"2026-06-14T05:22:58Z"},{"id":"10667635628","type":"WatchEvent","actor":{"id":21791,"login":"wilhelm-murdoch","display_login":"wilhelm-murdoch","gravatar_id":"","url":"https://api.github.com/users/wilhelm-murdoch","avatar_url":"https://avatars.githubusercontent.com/u/21791?"},"repo":{"id":426035190,"name":"wilhelm-murdoch/wilhelm.codes","url":"https://api.github.com/repos/wilhelm-murdoch/wilhelm.codes"},"payload":{"action":"started"},"public":true,"created_at":"2026-06-14T11:32:28Z"},{"id":"13294832656","type":"PushEvent","actor":{"id":21791,"login":"wilhelm-murdoch","display_login":"wilhelm-murdoch","gravatar_id":"","url":"https://api.github.com/users/wilhelm-murdoch","avatar_url":"https://avatars.githubusercontent.com/u/21791?"},"repo":{"id":426035190,"name":"wilhelm-murdoch/wilhelm.codes","url":"https://api.github.com/repos/wilhelm-murdoch/wilhelm.codes"},"payload":{"repository_id":426035190,"push_id":35582661827,"ref":"refs/heads/main","head":"eb484fb5aaf2ffb135bfde98658ce5228cb0fce6","before":"21259ef3b0dcf0d0f5bae3cb0ad2de15e5555c40"},"public":true,"created_at":"2026-06-14T06:27:37Z"},{"id":"13294686431","type":"PushEvent","actor":{"id":21791,"login":"wilhelm-murdoch","display_login":"wilhelm-murdoch","gravatar_id":"","url":"https://api.github.com/users/wilhelm-murdoch","avatar_url":"https://avatars.githubusercontent.com/u/21791?"},"repo":{"id":426035190,"name":"wilhelm-murdoch/wilhelm.codes","url":"https://api.github.com/repos/wilhelm-murdoch/wilhelm.codes"},"payload":{"repository_id":426035190,"push_id":35582515476,"ref":"refs/heads/main","head":"21259ef3b0dcf0d0f5bae3cb0ad2de15e5555c40","before":"ab673eedd8a3e73c6a072f03c5ef3f25e1347d9d"},"public":true,"created_at":"2026-06-14T06:20:31Z"},{"id":"13293800752","type":"PushEvent","actor":{"id":21791,"login":"wilhelm-murdoch","display_login":"wilhelm-murdoch","gravatar_id":"","url":"https://api.github.com/users/wilhelm-murdoch","avatar_url":"https://avatars.githubusercontent.com/u/21791?"},"repo":{"id":426035190,"name":"wilhelm-murdoch/wilhelm.codes","url":"https://api.github.com/repos/wilhelm-murdoch/wilhelm.codes"},"payload":{"repository_id":426035190,"push_id":35581628439,"ref":"refs/heads/main","head":"ab673eedd8a3e73c6a072f03c5ef3f25e1347d9d","before":"b693eef8c0ab2e3ab4bd36a744e90467bc4ba98a"},"public":true,"created_at":"2026-06-14T05:39:25Z"},{"id":"13293517413","type":"PushEvent","actor":{"id":21791,"login":"wilhelm-murdoch","display_login":"wilhelm-murdoch","gravatar_id":"","url":"https://api.github.com/users/wilhelm-murdoch","avatar_url":"https://avatars.githubusercontent.com/u/21791?"},"repo":{"id":426035190,"name":"wilhelm-murdoch/wilhelm.codes","url":"https://api.github.com/repos/wilhelm-murdoch/wilhelm.codes"},"payload":{"repository_id":426035190,"push_id":35581344775,"ref":"refs/heads/main","head":"b693eef8c0ab2e3ab4bd36a744e90467bc4ba98a","before":"300d4fceae16492238dba21ccec5d66a0ec8c8dc"},"public":true,"created_at":"2026-06-14T05:25:00Z"},{"id":"10663044878","type":"PullRequestEvent","actor":{"id":21791,"login":"wilhelm-murdoch","display_login":"wilhelm-murdoch","gravatar_id":"","url":"https://api.github.com/users/wilhelm-murdoch","avatar_url":"https://avatars.githubusercontent.com/u/21791?"},"repo":{"id":426035190,"name":"wilhelm-murdoch/wilhelm.codes","url":"https://api.github.com/repos/wilhelm-murdoch/wilhelm.codes"},"payload":{"action":"opened","number":8,"pull_request":{"url":"https://api.github.com/repos/wilhelm-murdoch/wilhelm.codes/pulls/8","id":3861880926,"number":8,"head":{"ref":"modernize","sha":"c549f29f71dc13066cb21410d68797c19332e7be","repo":{"id":426035190,"url":"https://api.github.com/repos/wilhelm-murdoch/wilhelm.codes","name":"wilhelm.codes"}},"base":{"ref":"main","sha":"300d4fceae16492238dba21ccec5d66a0ec8c8dc","repo":{"id":426035190,"url":"https://api.github.com/repos/wilhelm-murdoch/wilhelm.codes","name":"wilhelm.codes"}}}},"public":true,"created_at":"2026-06-14T05:22:58Z"},{"id":"13293469210","type":"CreateEvent","actor":{"id":21791,"login":"wilhelm-murdoch","display_login":"wilhelm-murdoch","gravatar_id":"","url":"https://api.github.com/users/wilhelm-murdoch","avatar_url":"https://avatars.githubusercontent.com/u/21791?"},"repo":{"id":426035190,"name":"wilhelm-murdoch/wilhelm.codes","url":"https://api.github.com/repos/wilhelm-murdoch/wilhelm.codes"},"payload":{"ref":"modernize","ref_type":"branch","full_ref":"refs/heads/modernize","master_branch":"main","description":"All source files for my personal website.","pusher_type":"user"},"public":true,"created_at":"2026-06-14T05:22:31Z"}]